radient/__init__.py
radient/_milvus.py
radient/factory.py
radient/vector.py
radient/orchestrate/__init__.py
radient/orchestrate/runners.py
radient/orchestrate/workflow.py
radient/tasks/__init__.py
radient/tasks/_base.py
radient/tasks/accelerate.py
radient/tasks/sinks/__init__.py
radient/tasks/sinks/_base.py
radient/tasks/sinks/milvus.py
radient/tasks/sources/__init__.py
radient/tasks/sources/_base.py
radient/tasks/sources/local.py
radient/tasks/sources/youtube.py
radient/tasks/transforms/__init__.py
radient/tasks/transforms/_base.py
radient/tasks/transforms/video_demux/__init__.py
radient/tasks/transforms/video_demux/_base.py
radient/tasks/transforms/video_demux/default.py
radient/tasks/transforms/video_demux/ffmpeg.py
radient/tasks/vectorizers/__init__.py
radient/tasks/vectorizers/_base.py
radient/tasks/vectorizers/_imagebind.py
radient/tasks/vectorizers/multimodal.py
radient/tasks/vectorizers/audio/__init__.py
radient/tasks/vectorizers/audio/_base.py
radient/tasks/vectorizers/audio/imagebind.py
radient/tasks/vectorizers/audio/torchaudio.py
radient/tasks/vectorizers/graph/__init__.py
radient/tasks/vectorizers/graph/_base.py
radient/tasks/vectorizers/graph/fastrp.py
radient/tasks/vectorizers/image/__init__.py
radient/tasks/vectorizers/image/_base.py
radient/tasks/vectorizers/image/imagebind.py
radient/tasks/vectorizers/image/timm.py
radient/tasks/vectorizers/molecule/__init__.py
radient/tasks/vectorizers/molecule/_base.py
radient/tasks/vectorizers/molecule/rdkit.py
radient/tasks/vectorizers/text/__init__.py
radient/tasks/vectorizers/text/_base.py
radient/tasks/vectorizers/text/cohere.py
radient/tasks/vectorizers/text/imagebind.py
radient/tasks/vectorizers/text/sbert.py
radient/tasks/vectorizers/text/sklearn.py
radient/tasks/vectorizers/text/voyage.py
radient/utils/__init__.py
radient/utils/flatten_inputs.py
radient/utils/lazy_import.py
radient-2024.8.19.dist-info/LICENSE
radient-2024.8.19.dist-info/METADATA
radient-2024.8.19.dist-info/WHEEL
radient-2024.8.19.dist-info/top_level.txt
radient-2024.8.19.dist-info/RECORD
