Metadata-Version: 2.1
Name: radient
Version: 2024.8.19
Summary: Turn unstructured data into vectors
Author-email: Frank Liu <frank@frankzliu.com>
Project-URL: Homepage, https://github.com/fzliu/radient
Project-URL: Issues, https://github.com/fzliu/radient/issues
Classifier: Programming Language :: Python :: 3
Classifier: License :: OSI Approved :: BSD License
Requires-Python: >=3.8
License-File: LICENSE
Requires-Dist: numpy >=1.19
Requires-Dist: pip >=20.1
Requires-Dist: graphlib-backport >=1.0.3 ; python_version <= "3.8"
